shadow_ai/__init__.py
shadow_ai/core/rule.py
shadow_ai/core/rule_combination.py
shadow_ai/core/rule_package.py
shadow_ai/core/shadow_ai.py
shadow_ai/core/table_rule.py
shadow_ai/rules/__init__.py
shadow_ai/rules/basic_rules.py
shadow_ai/rules/combinations.py
shadow_ai/rules/packages.py
shadow_ai/utils/__init__.py
shadow_ai/utils/file_utils.py
shadow_ai/utils/table_formatter.py
shadow_ai/utils/validators.py
shadowai-0.2.0.dist-info/licenses/LICENSE
shadowai-0.2.0.dist-info/METADATA
shadowai-0.2.0.dist-info/WHEEL
shadowai-0.2.0.dist-info/top_level.txt
shadowai-0.2.0.dist-info/RECORD
