Metadata-Version: 2.4
Name: shadowai
Version: 0.2.0
Summary: AI-powered mock data generation library with flexible rule engine and table generation support
Author-email: Kevin Zhang <kevinzhang19870314@gmail.com>
License: MIT
Project-URL: Homepage, https://github.com/KevinZhang19870314/shadowai
Project-URL: Documentation, https://github.com/KevinZhang19870314/shadowai#readme
Project-URL: Repository, https://github.com/KevinZhang19870314/shadowai
Project-URL: Bug Tracker, https://github.com/KevinZhang19870314/shadowai/issues
Keywords: ai,mock,data,generation,testing,agno,table,csv,markdown
Classifier: Development Status :: 4 - Beta
Classifier: Intended Audience :: Developers
Classifier: License :: OSI Approved :: MIT License
Classifier: Operating System :: OS Independent
Classifier: Programming Language :: Python :: 3
Classifier: Programming Language :: Python :: 3.8
Classifier: Programming Language :: Python :: 3.9
Classifier: Programming Language :: Python :: 3.10
Classifier: Programming Language :: Python :: 3.11
Classifier: Programming Language :: Python :: 3.12
Classifier: Topic :: Software Development :: Testing
Classifier: Topic :: Software Development :: Libraries :: Python Modules
Requires-Python: >=3.8
License-File: LICENSE
Requires-Dist: agno>=1.7.0
Requires-Dist: pydantic>=2.0.0
Requires-Dist: pyyaml>=6.0
Requires-Dist: typing-extensions>=4.0.0
Provides-Extra: dev
Requires-Dist: pytest>=7.0.0; extra == "dev"
Requires-Dist: pytest-cov>=4.0.0; extra == "dev"
Requires-Dist: black>=23.0.0; extra == "dev"
Requires-Dist: isort>=5.0.0; extra == "dev"
Requires-Dist: flake8>=6.0.0; extra == "dev"
Requires-Dist: mypy>=1.0.0; extra == "dev"
Provides-Extra: openai
Requires-Dist: agno[openai]; extra == "openai"
Provides-Extra: anthropic
Requires-Dist: agno[anthropic]; extra == "anthropic"
Provides-Extra: all
Requires-Dist: agno[anthropic,openai]; extra == "all"
Dynamic: license-file
